petite/__init__.py
petite/run.py
petite-0.1.0.dist-info/LICENSE
petite-0.1.0.dist-info/METADATA
petite-0.1.0.dist-info/WHEEL
petite-0.1.0.dist-info/top_level.txt
petite-0.1.0.dist-info/RECORD
